Workbook
Name MPCalc1: [1]Internals!$D$4
Name MPCalc10: [1]Internals!$D$13
Name MPCalc11: [1]Internals!$D$14
Name MPCalc12: [1]Internals!$D$15
Name MPCalc2: [1]Internals!$D$5
Name MPCalc3: [1]Internals!$D$6
Name MPCalc4: [1]Internals!$D$7
Name MPCalc5: [1]Internals!$D$8
Name MPCalc6: [1]Internals!$D$9
Name MPCalc7: [1]Internals!$D$10
Name MPCalc8: [1]Internals!$D$11
Name MPCalc9: [1]Internals!$D$12

Sheet Master Sheet
C1: Deal Analyzer for Rentals
C4: Property Address: | D4: 1500 Hemphill St. Charlotte, NC 28208
C5: Date
C7: INPUTS
C8: Leverage: | D8: 0.75 | F8: Marginal Tax Bracket: | J8: 0.28
C9: Appreciation: | D9: 0.05 | F9: Capital Gains Rate: | J9: 0.28
C10: Interest Rate: | D10: 0.0525 | F10: Value of the Land: | J10: 0.1
C11: # of Units | D11: 10 | F11: Total Square Footage | J11: 8918
C12: Market Cap Rate | D12: 0.1 | F12: Cash on Cash Return 1st Year | J12: =J55/E27 -> 0.093398098
C13: COMPARATIVE ANALYSIS
C14: Price Per Square Foot | E14: =E22/J11 -> 44.853106
C15: Price Per Unit | E15: =E22/D11 -> 40000
C16: Gross Rent Multiplier | E16: =J40/E22 -> 0.15
C17: Net Income Multiplier | E17: =(1/D12) -> 10
C18: Cap Rate | E18: =J53/E22 -> 0.0966325
C19: Present Market Value | E19: =E17*J53 -> 386530 | F19: **Only Yellow numbers should be replaced in top section of the Analyzer. Yellow block should be filled in below as well.
C21: PURCHASE ANALYSIS
C22: Purchase Price | E22: 400000
C23: Closing Costs | D23: 0.01 | E23: =0.01*E22 -> 4000
C24: Total Cost | E24: =SUM(E22:E23) -> 404000
C25: First Mortgage | D25: =D8 -> 0.75 | E25: =E22*D8 -> 300000
C26: Second Mortgage
C27: Down Payment | E27: =(E24-E25) -> 104000
C29: FINANCING ANALYSIS
C30: Interest Rate (r ) | F30: =D10/12 -> 0.004375 | G30: Payments Left | H30: Year | I30: Closing Loan Balance | J30: Amortization
C31: Term in Months (n) | F31: 180 | G31: =F31-12 -> 168 | H31: 1 | I31: =PV($F$30,G31,$F$34) -> 286488.35 | J31: =$F$32-I31 -> 13511.647
C32: Amount Borrowed (PV) | F32: =E25 -> 300000 | G32: =$F$31-24 -> 156 | H32: 2 | I32: =PV($F$30,G32,$F$34) -> 272250.02 | J32: =I31-I32 -> 14238.329
C33: Balloon Payment (FV) | F33: 0 | G33: =$F$31-36 -> 144 | H33: 3 | I33: =PV($F$30,G33,$F$34) -> 257245.93 | J33: =I32-I33 -> 15004.093
C34: Monthly Payment (D) | F34: =PMT(F30,F31,F32,F33) -> -2411.6331 | G34: =$F$31-48 -> 132 | H34: 4 | I34: =PV($F$30,G34,$F$34) -> 241434.89 | J34: =I33-I34 -> 15811.041
G35: =$F$31-60 -> 120 | H35: 5 | I35: =PV($F$30,G35,$F$34) -> 224773.5 | J35: =I34-I35 -> 16661.389
H36: Total Pay Down | I36: =SUM(J31:J35) -> 75226.498
C37: FIRST YEAR OPERATING PROJECTION
C38: Income/Expense | F38: Based on | I38: Monthly | J38: Annual
C40: Gross Scheduled Income/Net Rents | I40: 5000 | J40: =I40*12 -> 60000
C41: Vacancies | E41: 0.08 | I41: =J41/12 -> 400 | J41: =J40*E41 -> 4800
C42: Legal | I42: =J42/12 -> 0 | J42: 0
C43: Advertising | I43: =J43/12 -> 0 | J43: 0
C44: Cleaning | I44: =J44/12 -> 0 | J44: 0
C45: Miscellaneous | I45: =J45/12 -> 0 | J45: 0
C46: Insurance | I46: =J46/12 -> 166.66667 | J46: 2000
C47: Property Management % of Gross Rents | G47: 0.08 | I47: =J47/12 -> 368 | J47: =(J40-J41)*G47 -> 4416
C48: Property Taxes | I48: =J48/12 -> 344.25 | J48: 4131
C49: Water, Sewer, Electricity,Garbage | E49: 0.05 | I49: =J49/12 -> 250 | J49: =J40*E49 -> 3000
C50: Repairs and Maintenance | E50: 0.05 | I50: =J50/12 -> 250 | J50: =J40*E50 -> 3000
C51: TOTAL OPERATING EXPENSE | I51: =SUM(I42:I50) -> 1378.9167 | J51: =SUM(J42:J50) -> 16547
C52: GROSS OPERATING INCOME | I52: =J52/12 -> 4600 | J52: =J40-J41 -> 55200
C53: NET OPERATING INCOME | I53: =I52-I51 -> 3221.0833 | J53: =J52-J51 -> 38653
C54: Mortgage | I54: =F34 -> -2411.6331 | J54: =12*I54 -> -28939.598
C55: Cash Flow | I55: =I53+I54 -> 809.45019 | J55: =J53+J54 -> 9713.4022
C56: Operating Expense Ratio | J56: =J51/J52 -> 0.29976449
C57: Depreciation (affects TI not CF) | F57: 430000 | G57: Basis | H57: 39 | I57: =J57/12 -> 918.80342 | J57: =F57/H57 -> 11025.641
C58: Mortgage Interest | J58: =(-F34*12)-J31 -> 15427.951
C59: Taxable Income | J59: =(J53)-J57-((-F34*12)-J31) -> 12199.408
C61: Cash Flow | J61: =J55 -> 9713.4022
C62: Tax Cost | J62: =-J8*J59 -> -3415.8342
C63: After Tax Cash Flow | J63: =J61+J62 -> 6297.568
C64: Return on Equity | J64: =J63/E27 -> 0.060553539
C65: FIVE YEAR OPERATING PROJECTION:
C66: Income/Expense | E66: Escalator | F66: Year: 1 | G66: Year: 2 | H66: Year: 3 | I66: Year: 4 | J66: Year: 5
C67: Rent | E67: 0.03 | F67: =J40 -> 60000 | G67: =($E$67*F67)+F67 -> 61800 | H67: =($E$67*G67)+G67 -> 63654 | I67: =($E$67*H67)+H67 -> 65563.62 | J67: =($E$67*I67)+I67 -> 67530.529
C68: Vacancies | E68: 0 | F68: =J41 -> 4800 | G68: =($E$68*F68)+F68 -> 4800 | H68: =($E$68*G68)+G68 -> 4800 | I68: =($E$68*H68)+H68 -> 4800 | J68: =($E$68*I68)+I68 -> 4800
C69: Advertising | E69: 0 | F69: =J43 -> 0 | G69: =($E$69*F69)+F69 -> 0 | H69: =($E$69*G69)+G69 -> 0 | I69: =($E$69*H69)+H69 -> 0 | J69: =($E$69*I69)+I69 -> 0
C70: Cleaning and Maintenance | E70: 0 | F70: =J44 -> 0 | G70: =($E$69*F70)+F70 -> 0 | H70: =($E$69*G70)+G70 -> 0 | I70: =($E$69*H70)+H70 -> 0 | J70: =($E$69*I70)+I70 -> 0
C71: Contingency | E71: 0 | F71: =J45 -> 0 | G71: =($E$69*F71)+F71 -> 0 | H71: =($E$69*G71)+G71 -> 0 | I71: =($E$69*H71)+H71 -> 0 | J71: =($E$69*I71)+I71 -> 0
C72: Insurance | E72: 0.03 | F72: =J46 -> 2000 | G72: =($E$72*F72)+F72 -> 2060 | H72: =($E$72*G72)+G72 -> 2121.8 | I72: =($E$72*H72)+H72 -> 2185.454 | J72: =($E$72*I72)+I72 -> 2251.0176
C73: Property Mgt. | E73: 0 | F73: =J47 -> 4416 | G73: =(G67-G68)*0.08 -> 4560 | H73: =(H67-H68)*0.08 -> 4708.32 | I73: =(I67-I68)*0.08 -> 4861.0896 | J73: =(J67-J68)*0.08 -> 5018.4423
C74: Property Taxes | E74: 0.01 | F74: =J48 -> 4131 | G74: =($E$74*F74)+F74 -> 4172.31 | H74: =($E$74*G74)+G74 -> 4214.0331 | I74: =($E$74*H74)+H74 -> 4256.1734 | J74: =($E$74*I74)+I74 -> 4298.7352
C75: Water, Sewer, Garbage | E75: 0 | F75: =J49 -> 3000 | G75: =($E$69*F75)+F75 -> 3000 | H75: =($E$69*G75)+G75 -> 3000 | I75: =($E$69*H75)+H75 -> 3000 | J75: =($E$69*I75)+I75 -> 3000
C76: Repairs and Maintenance | E76: 0.03 | F76: =J50 -> 3000 | G76: =F76+(F76*0.03) -> 3090 | H76: =G76+(G76*0.03) -> 3182.7 | I76: =H76+(H76*0.03) -> 3278.181 | J76: =I76+(I76*0.03) -> 3376.5264
C77: TOTAL OPERATING EXPENSE | F77: =SUM(F68:F76) -> 21347 | G77: =SUM(G68:G76) -> 21682.31 | H77: =SUM(H68:H76) -> 22026.853 | I77: =SUM(I68:I76) -> 22380.898 | J77: =SUM(J68:J76) -> 22744.722
C78: NET OPERATING INCOME | F78: =F67-F77 -> 38653 | G78: =G67-G77 -> 40117.69 | H78: =H67-H77 -> 41627.147 | I78: =I67-I77 -> 43182.722 | J78: =J67-J77 -> 44785.807
C79: Debt Coverage Ratio | F79: =F78/-(F34*12) -> 1.335644 | G79: =G78/-($F34*12) -> 1.386256 | H79: =H78/-($F34*12) -> 1.4384148 | I79: =I78/-($F34*12) -> 1.4921673 | J79: =J78/-($F34*12) -> 1.5475615
C80: Break Even Ratio | F80: =((-$F34*12)+F77)/$J52 -> 0.91098909 | G80: =((-$F34*12)+G77)/$J52 -> 0.91706355 | H80: =((-$F34*12)+H77)/$J52 -> 0.92330527 | I80: =((-$F34*12)+I77)/$J52 -> 0.92971913 | J80: =((-$F34*12)+J77)/$J52 -> 0.93631013
C81: Mortgage | F81: =$J$54 -> -28939.598 | G81: =$J$54 -> -28939.598 | H81: =$J$54 -> -28939.598 | I81: =$J$54 -> -28939.598 | J81: =$J$54 -> -28939.598
C82: CASH FLOW | F82: =F78+F81 -> 9713.4022 | G82: =G78+G81 -> 11178.092 | H82: =H78+H81 -> 12687.549 | I82: =I78+I81 -> 14243.124 | J82: =J78+J81 -> 15846.209
C84: Depreciation | F84: =$J$57 -> 11025.641 | G84: =$J$57 -> 11025.641 | H84: =$J$57 -> 11025.641 | I84: =$J$57 -> 11025.641 | J84: =$J$57 -> 11025.641
C85: Pay Down on Mortgage | F85: =J31 -> 13511.647 | G85: =J32 -> 14238.329 | H85: =J33 -> 15004.093 | I85: =J34 -> 15811.041 | J85: =J35 -> 16661.389
C86: TAXABLE INCOME | F86: =F82-F84+F85 -> 12199.408 | G86: =G82-G84+G85 -> 14390.78 | H86: =H82-H84+H85 -> 16666.001 | I86: =I82-I84+I85 -> 19028.524 | J86: =J82-J84+J85 -> 21481.957
C88: Cash Flow | F88: =F82 -> 9713.4022 | G88: =G82 -> 11178.092 | H88: =H82 -> 12687.549 | I88: =I82 -> 14243.124 | J88: =J82 -> 15846.209
C89: Tax Savings | F89: =-$J$8*F86 -> -3415.8342 | G89: =-$J$8*G86 -> -4029.4183 | H89: =-$J$8*H86 -> -4666.4802 | I89: =-$J$8*I86 -> -5327.9868 | J89: =-$J$8*J86 -> -6014.948
C90: AFTER TAX CASH FLOW | F90: =SUM(F88:F89) -> 6297.568 | G90: =SUM(G88:G89) -> 7148.6739 | H90: =SUM(H88:H89) -> 8021.0689 | I90: =SUM(I88:I89) -> 8915.1374 | J90: =SUM(J88:J89) -> 9831.2614
C91: SALES ANALYSIS AFTER 5 YEARS | M91: Appreciation Schedule
C92: Purchase Price | I92: =E22 -> 400000 | M92: Yr1-2 | N92: Yr2-3 | O92: Yr3-4 | P92: Yr4-5
C93: Appreciation | I93: =P93 -> 486202.5 | M93: =(I92*$D$9)+I92 -> 420000 | N93: =(M93*$D$9)+M93 -> 441000 | O93: =(N93*$D$9)+N93 -> 463050 | P93: =(O93*$D$9)+O93 -> 486202.5
C94: Loan Balance End of 5 years | I94: =I35 -> 224773.5
C95: Estimated Closing Costs | H95: 0.02 | I95: =I93*H95 -> 9724.05
C96: Real Estate Commission | H96: 0.03 | I96: =I93*H96 -> 14586.075
C97: Net Proceeds of Sale | I97: =I93-I94-I95-I96 -> 237118.87
C98: Adjusted Basis | I98: =G100+I95-I101 -> 358595.84
C100: Actual Capital Gain | F100: =I93-I95 -> 476478.45 | G100: =E24 -> 404000 | I100: =F100-G100 -> 72478.45
C101: Accumulated Depreciation | I101: =5*J57 -> 55128.205
C102: Taxable Capital Gain | I102: =SUM(I100:I101) -> 127606.66
C103: Income Tax | H103: =J9 -> 0.28 | I103: =I102*H103 -> 35729.863
C104: RATE OF RETURN AFTER 5 YEARS
C105: Purchase PV | F105: Year: 1 | G105: Year: 2 | H105: Year: 3 | I105: Year: 4 | J105: Year: 5
F106: D1 | G106: D2 | H106: D3 | I106: D4 | J106: D5
C107: Down Payment | E107: =-E27 -> -104000
C108: Cash Flow | F108: =F88 -> 9713.4022 | G108: =G88 -> 11178.092 | H108: =H88 -> 12687.549 | I108: =I88 -> 14243.124 | J108: =J88 -> 15846.209
C109: Net Proceeds of Sale | J109: =I97 -> 237118.87
C110: Cash Flow (before Tax) | E110: =E107 -> -104000 | F110: =SUM(F108:F109) -> 9713.4022 | G110: =SUM(G108:G109) -> 11178.092 | H110: =SUM(H108:H109) -> 12687.549 | I110: =SUM(I108:I109) -> 14243.124 | J110: =SUM(J108:J109) -> 252965.08
...

Sheet Sheet3

Sheet Single DCF
A1: Future Sales Price
B3: Single DCF
A4: Periodic Rate | C4: 0.1
A5: No. of Periods | C5: 5
A6: Sales Price | B6: 2500000 | C6: =-PV(C4,C5,,B6) -> 1552303.3

Sheet DCF
A1: Discounted Cash Flow
A4: Periodic Rate | C4: 0.1
A5: DCF Year 1 | B5: ='Master Sheet'!F82 -> 9713.4022 | C5: =-PV($C$4,1,,B5) -> 8830.3657
A6: DCF Year 2 | B6: ='Master Sheet'!G82 -> 11178.092 | C6: =-PV($C$4,2,,B6) -> 9238.0928
A7: DCF Year 3 | B7: ='Master Sheet'!H82 -> 12687.549 | C7: =-PV($C$4,3,,B7) -> 9532.3435
A8: DCF Year 4 | B8: ='Master Sheet'!I82 -> 14243.124 | C8: =-PV($C$4,4,,B8) -> 9728.2455
A9: DCF Year 5 | B9: ='Master Sheet'!J82+'Master Sheet'!I97 -> 252965.08 | C9: =-PV($C$4,5,,B9) -> 157071.41
A10: DCF | B10: 0 | C10: =-PV($C$4,6,,B10) -> 0
A11: DCF | B11: 0 | C11: =-PV($C$4,7,,B11) -> 0
A12: DCF | B12: 0 | C12: =-PV($C$4,8,,B12) -> 0
A13: DCF | B13: 0 | C13: =-PV($C$4,9,,B13) -> 0
A14: DCF | B14: 0 | C14: =-PV($C$4,10,,B14) -> 0
A15: PV of Future Cash Flow | C15: =SUM(C5:C14) -> 194400.46
A16: TOTAL NPV | C16: =C15-'Master Sheet'!E27 -> 90400.461
A17: PROFITABILITY INDEX | C17: =C15/'Master Sheet'!E27 -> 1.8692352

Sheet Balloon Payment
A1: Interest Rate (r ) | D1: ='Master Sheet'!F30 -> 0.004375 | E1: Payments Left | F1: Year | G1: Closing Loan Balance | H1: Amortization
A2: Term in Months (n) | D2: ='Master Sheet'!F31 -> 180 | E2: ='Master Sheet'!G31 -> 168 | F2: 1 | G2: =PV($D$1,E2,$D$4,,0) -> 286488.35 | H2: ='Master Sheet'!J31 -> 13511.647
A3: Amount Borrowed (PV) | D3: ='Master Sheet'!F32 -> 300000 | E3: =E2-12 -> 156 | F3: 2 | G3: =PV($D$1,E3,$D$4,,0) -> 272250.02 | H3: =G2-G3 -> 14238.329
A4: Monthly Payment (D) | D4: ='Master Sheet'!F34 -> -2411.6331 | E4: =E3-12 -> 144 | F4: 3 | G4: =PV($D$1,E4,$D$4,,0) -> 257245.93 | H4: =G3-G4 -> 15004.093
E5: =E4-12 -> 132 | F5: 4 | G5: =PV($D$1,E5,$D$4,,0) -> 241434.89 | H5: =G4-G5 -> 15811.041
E6: =E5-12 -> 120 | F6: 5 | G6: =PV($D$1,E6,$D$4,,0) -> 224773.5 | H6: =G5-G6 -> 16661.389
E7: =E6-12 -> 108 | F7: 6 | G7: =PV($D$1,E7,$D$4,,0) -> 207216.03 | H7: =G6-G7 -> 17557.47
E8: =E7-12 -> 96 | F8: 7 | G8: =PV($D$1,E8,$D$4,,0) -> 188714.29 | H8: =G7-G8 -> 18501.744
E9: =E8-12 -> 84 | F9: 8 | G9: =PV($D$1,E9,$D$4,,0) -> 169217.49 | H9: =G8-G9 -> 19496.802
E10: =E9-12 -> 72 | F10: 9 | G10: =PV($D$1,E10,$D$4,,0) -> 148672.11 | H10: =G9-G10 -> 20545.377
E11: =E10-12 -> 60 | F11: 10 | G11: =PV($D$1,E11,$D$4,,0) -> 127021.76 | H11: =G10-G11 -> 21650.346
E12: =E11-12 -> 48 | F12: 11 | G12: =PV($D$1,E12,$D$4,,0) -> 104207.02 | H12: =G11-G12 -> 22814.743
E13: =E12-12 -> 36 | F13: 12 | G13: =PV($D$1,E13,$D$4,,0) -> 80165.258 | H13: =G12-G13 -> 24041.763
E14: =E13-12 -> 24 | F14: 13 | G14: =PV($D$1,E14,$D$4,,0) -> 54830.484 | H14: =G13-G14 -> 25334.774
E15: =E14-12 -> 12 | F15: 14 | G15: =PV($D$1,E15,$D$4,,0) -> 28133.158 | H15: =G14-G15 -> 26697.326
E16: =E15-12 -> 0 | F16: 15 | G16: =PV($D$1,E16,$D$4,,0) -> 0 | H16: =G15-G16 -> 28133.158
... E31: =E30-12 -> -180 | F31: 30 | G31: =PV($D$1,E31,$D$4,,0) -> -658236.85 | H31: =G30-G31 -> 61727.606
