Workbook
Name _ProjectsArray: '[1]Project List'!$A$6:$J$49
Name BuiltIn_AutoFilter___1: #REF!
Name BuiltIn_AutoFilter___1: #REF!
Name BuiltIn_AutoFilter___1: #REF!
Name BuiltIn_AutoFilter___1: #REF!
Name BuiltIn_AutoFilter___1: #REF!
Name BuiltIn_AutoFilter___1_1: #REF!
Name BuiltIn_AutoFilter___1_1: #REF!
Name BuiltIn_AutoFilter___1_1: #REF!
Name BuiltIn_AutoFilter___1_1: #REF!
Name BuiltIn_AutoFilter___1_1: #REF!
Name BuiltIn_AutoFilter___1_2: #REF!
Name BuiltIn_AutoFilter___1_2: #REF!
Name BuiltIn_AutoFilter___1_2: #REF!
Name BuiltIn_AutoFilter___1_2: #REF!
Name BuiltIn_AutoFilter___1_2: #REF!
Name BuiltIn_AutoFilter___1_3: #REF!
Name BuiltIn_AutoFilter___1_3: #REF!
Name BuiltIn_AutoFilter___1_3: #REF!
Name BuiltIn_AutoFilter___1_3: #REF!
Name BuiltIn_AutoFilter___1_4: #REF!
Name BuiltIn_AutoFilter___1_4: #REF!
Name BuiltIn_AutoFilter___1_4: #REF!
Name BuiltIn_AutoFilter___1_4: #REF!
Name BuiltIn_AutoFilter___1_5: #REF!
Name BuiltIn_AutoFilter___1_5: #REF!
Name BuiltIn_AutoFilter___1_5: #REF!
Name BuiltIn_AutoFilter___1_5: #REF!
Name Category: OFFSET([2]Lookup!$C$2,0,0,MIN(COUNTA([2]Lookup!$C$2:$C$100)))
Name Design: '[1]Project List'!$F$6:$F$49
Name Development: '[1]Project List'!$H$6:$H$49
Name Editorial: '[1]Project List'!$G$6:$G$49
Name Endorsement: '[1]Project List'!$E$6:$E$49
Name holidays: OFFSET([3]Holidays!$A$10,1,0,COUNTA([3]Holidays!$A$11:$A$4996),1)
Name Launch: '[1]Project List'!$J$6:$J$49
Name LOB: OFFSET([2]Lookup!$D$2,0,0,MIN(COUNTA([2]Lookup!$D$2:$D$100)))
Name Ok: #REF!
Name Ok: #REF!
Name Priority: OFFSET([2]Lookup!$B$2,0,0,MIN(COUNTA([2]Lookup!$B$2:$B$100)))
Name ProcApp: #REF!
Name ProcApp: #REF!
Name ProcApp: #REF!
Name ProcApp: #REF!
Name ProcApp: #REF!
Name RowOffset: '[1]Project List'!$I$1
Name sort_range: '[4]Open Issues'!$3:$681
Name sort_range: '[5]Open Issues'!$3:$681
Name Spec: '[1]Project List'!$D$6:$D$49
Name Stat: '[6]Site Release Action Items List'!$E:$E
Name Status: OFFSET([2]Lookup!$A$2,0,0,MIN(COUNTA([2]Lookup!$A$2:$A$100)))
Name statuslist: #REF!
Name statuslist: #REF!
Name statuslist: #REF!
Name statuslist: #REF!
Name statuslist: #REF!
Name Testing: '[1]Project List'!$I$6:$I$49
Name valuevx: 42.314159
Name Years: OFFSET([2]Lookup!$L$2,0,0,MIN(COUNTA([2]Lookup!$L$2:$L$20)))

Sheet Deal Information
B1: Deal Information
AG2: Y | AH2: ARV
AG3: N | AH3: Purchase+Rehab
AH4: Purchase Price
B7: PROPERTY DETAILS | G7: PROJECT DETAILS
B8: Property Address: | C8: 123 Main Street | G8: Date: | H8: 41274
B9: Bed: | C9: 3 | G9: Occupied: | H9: N
B10: Bath: | C10: 2 | G10: Evaluator: | H10: Bill Smith
B11: Total Sqft: | C11: 1200 | G11: Closing Date: | H11: 41275
B12: # of Units: | C12: 1 | G12: Exit Strategy: | H12: Sell to my Friend
B14: PROPERTY DESCRIPTION
B15: This is a 3 bed house located in downtown area of Smithsville. Perfect for the first time home buyer. Needs some renovations.
B20: DEAL FACTORS | E20: FINANCING COSTS | I20: BUYING COSTS
B21: After Repair Value: | C21: 200000 | E21: First Mortgage / Lien Amount | G21: 0.75 | I21: Title Insurance / Search Costs | J21: 0.0025
B22: "As Is" Value: | C22: 50000 | E22: First Mortgage Points | G22: 0 | I22: Miscellaneous Buying Costs | J22: 0
B23: Purchase Price: | C23: 50000 | E23: First Mortgage Interest | G23: 0.12 | I23: Escrow / Attorney Fees | J23: 500
B24: Hold Time (months): | C24: 4
B25: Property Taxes (annually): | C25: 1000 | E25: Second Mortgage / Lien Amount | G25: 0 | I25: SELLING COSTS
B26: Insurance (annually): | C26: 500 | E26: Second Mortgage Points | G26: 0 | I26: Realtor Fees | J26: 0.03
B27: HOA & Condo Fees (monthly): | C27: 0 | E27: Second Mortgage Interest | G27: 0 | I27: Transfer & Conveyance Fees | J27: 0.0012
B28: Gas: | C28: 100 | I28: Miscellaneous Selling Costs | J28: 0
B29: Water: | C29: 50 | E29: Misc. Mortgage / Lien Amount | G29: 0 | I29: Staging Costs | J29: 0
B30: Electricity: | C30: 100 | E30: Misc. Mortgage Points | G30: 0 | I30: Escrow / Attorney Fees | J30: 500
B31: Other Utilities: | C31: 0 | E31: Misc. Mortgage Interest | G31: 0 | I31: Selling Recording Fees | J31: 350
B32: Miscellaneous Holding Costs: | C32: 0 | E32: Miscellaneous Financing Costs | I32: Home Warranty | J32: 500
I33: Marketing Costs | J33: 500
A36: COMPARABLES
B38: PROPERTY 1 | E38: PROPERTY 2 | I38: PROPERTY 3
B39: Address | C39: 123 Main Street | E39: Address | I39: Address
B40: Type | C40: SFH | E40: Type | I40: Type
B41: Bed | C41: 3 | E41: Bed | I41: Bed
B42: Bath | C42: 2 | E42: Bath | I42: Bath
B43: Size (Sqft) | C43: 1200 | E43: Size (Sqft) | I43: Size (Sqft)
B44: Land Size | C44: 1290 | E44: Land Size | I44: Land Size
B45: Year Built | C45: 1982 | E45: Year Built | I45: Year Built
B46: Distance | C46: 1 | E46: Distance | I46: Distance
B47: Parking | C47: 1 Car | E47: Parking | I47: Parking
B48: List Date | C48: 41305 | E48: List Date | I48: List Date
B49: List Price | C49: 135000 | E49: List Price | I49: List Price
B50: Sold Date | C50: 41306 | E50: Sold Date | I50: Sold Date
B51: Sold Price | C51: 135000 | E51: Sold Price | I51: Sold Price
B52: Price Sqft | C52: 65 | E52: Price Sqft | I52: Price Sqft
B53: DOM | E53: DOM | I53: DOM

Sheet Definitions
A1: Deal Information Tab
A2: PROPERTY DETAILS
A3: Property Address | B3: The address of the property you want to analyze
A4: Bed | B4: Total number of bedrooms in the property
A5: Bath | B5: Total number of bathrooms in the property
A6: Total Square Footage | B6: The total square footage of the entire interior of the property
A7: Number of Units | B7: Number of units in the property
A8: PROJECT DETAILS
A9: Date | B9: Date of this analysis
A10: Occupied | B10: Select Yes or No from the drop down
A11: Evaluator Name | B11: Name of the person that evaluated the property
A12: Closing Date | B12: Estimated date to close on the property
A13: Exit Strategy | B13: Expected plan for the property once it's been rehabbed, including, presale, traditional sale, rental property, etc
A14: DEAL FACTORS
A15: After Repair Value | B15: Value of the property after all repairs have been made regadless of purchase price. Also known as "Fair Market Value"
A16: "As Is" Value | B16: Value of the property in current "as is" condition. Not factoring repairs needed
A17: Purchase Price | B17: The dollar amount you plan to purchase the property for
A18: Estimated Repair Costs | B18: The dollar amount of estimated repairs based on your analysis, or select "Load from Hammerpoint Estimate"
A19: Hold Time (months) | B19: Estimated number of months you plan to own the property from purhase date to close of escrow sale date
A20: Property Taxes (annually) | B20: Enter the annual property taxes as reported on the county tax assessors website or enter an estimate
A21: Insurance (annually) | B21: Enter the property insurance premium here typically billed monthly. Vacant properties typically cost more than occupied.
A22: HOA & Condo Fees (monthly) | B22: Enter the Home Owner Association fees typically charged monthly here. If paid quarterly, divide the amount by 3
A23: Gas (monthly) | B23: Estimated monthly cost of gas bill while you own the property
A24: Water (monthly) | B24: Estimated monthly cost of water bill while you own the property
A25: Electricity (monthly) | B25: Estimated monthly cost of electric bil while you own the property
A26: Other Utiliites (monthly) | B26: Estimated monthly cost of other utilities used while you own the property
A27: Miscellaneous Holding Costs | B27: Enter any custom costs related to holding the property
A28: FINANCING COSTS
A29: First Mortgage / Lien Amount | B29: The 1st position loan amount borrowed to purchase the property and / or fund the rehab
A30: First Mortgage Points | B30: The 1st position points charged as a % of Mortgage Lien Amount. 1 Point = 1% in calculation.
A31: First Mortgage Interest | B31: The 1st position Interest rate amount borrowed to purchase the property and / or fund the rehab
A32: Second Mortgage / Lien Amount | B32: The 2nd position loan amount borrowed to purchase the property and / or fund the rehab
A33: Second Mortgage Points | B33: The 2nd position points charged as a % of Mortgage Lien Amount. 1 Point = 1% in calculation.
A34: Second Mortgage Interest | B34: The 2nd position Interest rate amount borrowed to purchase the property and / or fund the rehab
A35: Misc. Mortgage / Lien Amount | B35: An additional amount borrowed to fund the rehab repair costs for the property
A36: Misc. Mortgage Points | B36: An additional position points charged as a % of Mortgage Lien Amount. 1 Point = 1% in calculation.
A37: Misc. Mortgage Interest | B37: An additional Interest rate amount borrowed to purchase the property and / or fund the rehab
A38: Miscellaneous Financing Costs | B38: Any custom costs related to Financing. This is a custom naming field which you can modify by clicking the EDIT button to the right.
A39: BUYING COSTS
A40: Title Insurance / Title Search Costs | B40: Policy to insure clear and marketable title. Changes based on area, type of policy, underwriter
A41: Miscellaneous Buying Costs | B41: Enter any additional custom costs related to Buying transactions.
A42: Escrow / Attorney Fees | B42: Fees charged by attorney or escrow company at closing. Typically a % of sales price. Fees vary by Attorney or Escrow state.
A43: SELLING COSTS
A44: Realtor Fees | B44: Commissions paid to realtors involved as part of the transaction
A45: Transfer & Conveyance Fees | B45: For the transfer of land charged by County from seller to buyer. Typically a % of the land value based on county assessor valuation
A46: Miscellaneous Selling Costs | B46: Enter any additional custom costs related to Selling transactions.
A47: Staging Costs | B47: Cost for getting property ready to sell by bringing in furnishings so the property will show as if someone lived there
A48: Escrow / Attorney Fees | B48: Fees charged by attorney or escrow company at closing. Typically a % of sales price. Fees vary by Attorney or Escrow state.
A49: Selling Recording Fees | B49: Fees taken from the HUD-1 County recorders fees charged by escrow company
A50: Home Warranty | B50: Offers protection for mechanical systems and attached appliances against unexpected repairs not covered by homeowner's insurance; overage extends over a specific time period and does not cover the home's structure
A51: Marketing Costs | B51: Costs related to offline and online advertising, printing, and promotion to help sell the property.
A52: Deal Analyzer Tab
A53: Estimated NET PROFIT | B53: Difference between the revenue and expenses of the entire project before income taxes.
A54: Total Costs Return on Investment (ROI) | B54: % of interest earned based on purchase +ALL costs irregardless of how long the property was held
A55: PURCHASE & DEAL ANALYSIS
A56: Total Financing Costs | B56: Total Borrowing Costs of first, second, and rehab financing fees, points, and interest charged over duration of the project
A57: Total Holding Costs | B57: Total Costs for all monthly carrying expenses based on the duration of how long property is held between purchase and sales date.
A58: Total Buying Transaction Costs | B58: Total transactional costs related to the buying phase of the transaction
A59: Total Selling Transaction Costs | B59: Total transactional costs related to the selling phase of the transaction.
A60: POTENTIAL RETURN & PROFIT ANALYSIS
A61: Potential Return & Profit Analysis | B61: Section Summary of key profit and deal value measurements
A62: Purchase + Repair Estimate Cost Per Sq. Ft | B62: Total Purchase+Rehab Estimate costs divided by total square feet of the property used as a measurement market indicator
A63: Down Payment Required at Closing | B63: Amount of funds needed at time of closing to purchase the property
A64: My Committed Capital | B64: Amount of your own money out of pocket that you put in the deal as the purchaser
A65: My Annualized Cash on Cash Return | B65: % of interest estimated that you would earn over a year period based on your out of pocket funds that you put into the deal as a purchaser.
A66: Total Annualized Cash on Cash Return | B66: % of interest earned based on purchase price + all other costs over a 12 month annualized period
A67: Purchase + Rehab Return on Investment (ROI) | B67: % of interest earned based on purchase + rehab costs irregardless of how long the property was held.

Sheet Deal Analyzer for Flips
B1: Deal Analyzer
BC2: Y | BD2: ARV | BE2: =SUM('Deal Information'!C11:E11) -> 1200
BC3: N | BD3: Purchase+Rehab
BD4: Purchase Price
B6: Property Address: | C6: 123 Main Street | F6: # of Units: | G6: 1
B7: Total Square Footage: | C7: 1200 | F7: Date: | G7: 1.01.2017
B8: Evaluator Name: | C8: Bill Smith
B9: Property Description: | C9: Single Family Colonial in Smithville | F9: Occupied? (Y/N) | G9: N
B12: PROPERTY VALUES & PRICING | F12: HOLDING COSTS | G12: Annually | H12: Monthly
B13: After Repair Value | D13: =SUM('Deal Information'!C21) -> 200000 | F13: Property Taxes | G13: =SUM('Deal Information'!C25) -> 1000 | H13: =G13/12 -> 83.333333
B14: Current "As Is" Value | D14: =SUM('Deal Information'!C22) -> 50000 | F14: HOA & Condo Fees | G14: =SUM(H14*12) -> 0 | H14: =SUM('Deal Information'!C27) -> 0
B15: Estimated Repair Costs | D15: =SUM('Repair Estimator'!G239:K239) -> 0 | F15: Insurance Costs | G15: =SUM('Deal Information'!C26) -> 500 | H15: =G15/12 -> 41.666667
B16: Purchase Price | D16: =SUM('Deal Information'!C23) -> 50000 | F16: Utility Costs | H16: =SUM('Deal Information'!C28:C31) -> 250
B17: Estimated Hold Time (months) | D17: =SUM('Deal Information'!C24) -> 4 | F17: Miscellaneous Holding Costs | H17: =SUM('Deal Information'!C32) -> 0
B18: Total Purchase & Repair Cost | F18: Total Monthly Holding Costs
B19: =SUM(D15:D16) -> 50000 | F19: =SUM(H13:H17) -> 375
B21: Click to Select How to Calculate Your Loan ==>> | F21: ARV
B23: FINANCING COSTS | F23: BUYING TRANSACTION COSTS | G23: % of Purchase | H23: Total
B24: First Mortgage / Lien Amount | C24: =SUM('Deal Information'!G21) -> 0.75 | D24: =IF($F$21="ARV",$D$13*C24,IF($F$21="Purchase+Rehab",(($D$16+$D$15)*C24),IF($F$21="Purchase Price",($D$16*C24)))) -> 150000 | F24: Escrow / Attorney Fees | H24: =SUM('Deal Information'!J23) -> 500
B25: First Mortgage Points | C25: =SUM('Deal Information'!G22) -> 0 | D25: =C25/100*D24 -> 0 | F25: Title Insurance / Search Costs | G25: =SUM('Deal Information'!J21) -> 0.0025 | H25: =(500)+(G25*D16) -> 625
B26: First Mortgage Interest | C26: =SUM('Deal Information'!G23) -> 0.12 | D26: =D24*C26/12*D17 -> 6000 | F26: Miscellaneous Buying Costs | H26: =SUM('Deal Information'!J22) -> 0
B27: First Mortgage Monthly Interest Only Payment | D27: =D26/D17 -> 1500 | F27: Total Buying Transaction Cost
F28: =SUM(H24:H26) -> 1125
B29: Second Mortgage / Lien Amount | C29: =SUM('Deal Information'!G25) -> 0 | D29: =IF($F$21="ARV",$D$13*C29,IF($F$21="Purchase+Rehab",(($D$16+$D$15)*C29),IF($F$21="Purchase Price",($D$16*C29)))) -> 0
B30: Second Mortgage Points | C30: =SUM('Deal Information'!G26) -> 0 | D30: =C30/100*D29 -> 0
B31: Second Mortgage Interest | C31: =SUM('Deal Information'!G27) -> 0 | D31: =D29*C31/12*D17 -> 0 | F31: SELLING TRANSACTION COSTS | G31: % of ARV | H31: Total
B32: Second Mortgage Monthly Interest Only Payment | D32: =D31/D17 -> 0 | F32: Escrow / Attorney Fees | H32: =SUM('Deal Information'!J30) -> 500
F33: Selling Recording Fees | H33: =SUM('Deal Information'!J31) -> 350
B34: Misc. Mortgage / Lien Amount | C34: =SUM('Deal Information'!G29) -> 0 | D34: =IF($F$21="ARV",$D$13*C34,IF($F$21="Purchase+Rehab",(($D$16+$D$15)*C34),IF($F$21="Purchase Price",($D$16*C34)))) -> 0 | F34: Realtor Fees | G34: =SUM('Deal Information'!J26) -> 0.03 | H34: =G34*D13 -> 6000
B35: Misc. Mortgage Points | C35: =SUM('Deal Information'!G30) -> 0 | D35: =C35/100*D34 -> 0 | F35: Transfer & Conveyance Fees | G35: =SUM('Deal Information'!J27) -> 0.0012 | H35: =G35*D13 -> 240
B36: Misc. Mortgage Interest | C36: =SUM('Deal Information'!G31) -> 0 | D36: =D34*C36/12*D17 -> 0 | F36: Home Warranty | H36: =SUM('Deal Information'!J32) -> 500
B37: Misc. Mortgage Monthly Interest Only Payment | D37: =D36/D17 -> 0 | F37: Staging Costs | H37: =SUM('Deal Information'!J29) -> 0
F38: Marketing Costs | H38: =SUM('Deal Information'!J33) -> 500
B39: Miscellaneous Financing Costs | D39: =SUM('Deal Information'!G32) -> 0 | F39: Miscellaneous Selling Costs | H39: 0
B40: Total Financing Costs | F40: Total Selling Transaction Cost
B41: =SUM(D25,D26,D30,D31,D35,D36,D39) -> 6000 | F41: =SUM(H32:H39) -> 8090
A43: ESTIMATED NET PROFIT & ROI SNAPSHOT
B45: ESTIMATED NET PROFIT | F45: TOTAL COSTS RETURN ON INVESTMENT (ROI)
B46: =D49-D50-D51-D52-D53-D54-D55 -> 133285 | F46: =B46/(D50+D51+D52+D53+D54+D55) -> 1.9978266
B48: PURCHASE & DEAL ANALYSIS | F48: POTENTIAL RETURN & PROFIT ANALYSIS
B49: After Repair Value | D49: =D13 -> 200000 | F49: Assumes Sale is on or before | H49: ='Deal Information'!H8:J8+(D17*30) -> 41394
B50: Purchase Price | D50: =D16 -> 50000 | F50: Purchase + Repair Estimate Cost Per Sq. Ft | H50: =SUM(D50+D51)/BE2 -> 41.666667
B51: Estimated Repair Costs | D51: =D15 -> 0 | F51: Down Payment Required at Closing | H51: =D50+H27+D25+D30+D35-D24-D29-D34 -> -100000
B52: Total Financing Costs | D52: =SUM(B41) -> 6000 | F52: My Committed Capital | H52: =D50+D51+D25+D30+D35+D53+D54+H37+H38+H39-D24-D29-D34 -> -96875
B53: Total Holding Costs | D53: =SUM(D17*F19) -> 1500 | F53: My Annualized Cash on Cash Return | H53: =B46/H52*12/D17 -> -4.1275355
B54: Total Buying Transaction Costs | D54: =SUM(F28) -> 1125 | F54: Total Annualized Cash on Cash Return | H54: =F46*(12/D17) -> 5.9934797
B55: Total Selling Transaction Costs | D55: =SUM(F41) -> 8090 | F55: Purchase + Rehab Return on Investment (ROI) | H55: =B46/(D50+D51) -> 2.6657

Sheet Repair Estimator
A1: Repair Estimator
A2: Address: | B2: ='Deal Information'!$C$8 -> 123 Main Street | G2: Vacant: | H2: ='Deal Information'!$H$9 -> N | K2: Date: | N2: About the Repair Estimator
A3: Bed: | B3: =SUM('Deal Information'!C9:E9) -> 3 | D3: Bath: | E3: =SUM('Deal Information'!C10:E10) -> 2 | F3: Sq Ft: | G3: =SUM('Deal Information'!C11:E11) -> 1200 | J3: Inspected By:
A4: * Additional Mediator/Engineer/Pro Quotes Needed:
A7: EXTERIOR
A8: Category | C8: Y/N | D8: Repair Type | I8: # | J8: Unit | K8: Cost | L8: Total
A9: Roof * | D9: Roof (rip and replace) - architectural shingle | J9: psf | K9: 4 | L9: =SUM(I9*K9) -> 0
A10: Possible additional Inspections, Quotes or Mediation needed | D10: Rollover (add a layer of shingles) - architectural shingle | J10: psf | K10: 2.5 | L10: =SUM(I10*K10) -> 0
D11: Roof Sheathing - plywood 1/2" remove & install | J11: psf | K11: 2 | L11: =SUM(I11*K11) -> 0
D12: Roof repair/patch (hard) | J12: ea | K12: 900 | L12: =SUM(I12*K12) -> 0
D13: Roof repair/patch (easy) | J13: ea | K13: 600 | L13: =SUM(I13*K13) -> 0
D14: Premium for 3 layer tear off | J14: psf | K14: 0.35 | L14: =SUM(I14*K14) -> 0
D15: Premium for steep pitched roof | J15: psf | K15: 0.2 | L15: =SUM(I15*K15) -> 0
D16: Fascia - demo & install new | J16: lf | K16: 3 | L16: =SUM(I16*K16) -> 0
D17: Soffit - demo & install new | J17: lf | K17: 4 | L17: =SUM(I17*K17) -> 0
A18: Gutters | D18: Gutters & downspouts - demo & install new (Flat Cost) | J18: psf | K18: 0.5 | L18: =SUM(I18*K18) -> 0
D19: Gutters & downspouts - demo & install new (linear foot) | J19: lf | K19: 6 | L19: =SUM(I19*K19) -> 0
A20: Finish | D20: Demo existing finishing material | J20: psf | K20: 0.75 | L20: =SUM(I20*K20) -> 0
D21: Stucco | J21: psf | K21: 7 | L21: =SUM(I21*K21) -> 0
D22: Wood siding | J22: psf | K22: 6 | L22: =SUM(I22*K22) -> 0
D23: Vinyl siding | J23: psf | K23: 2.25 | L23: =SUM(I23*K23) -> 0
D24: Fiber cement siding | J24: psf | K24: 7 | L24: =SUM(I24*K24) -> 0
D25: Plywood panel siding | J25: psf | K25: 2.5 | L25: =SUM(I25*K25) -> 0
D26: Patch an exterior section | J26: ls | K26: 500 | L26: =SUM(I26*K26) -> 0
D27: Power wash exterior finish | J27: psf | K27: 0.75 | L27: =SUM(I27*K27) -> 0
A28: Masonry | D28: Fireplace/chimney, brick/stone - replace existing | J28: ls | K28: 5000 | L28: =SUM(I28*K28) -> 0
D29: Concrete block | J29: sf | K29: 6 | L29: =SUM(I29*K29) -> 0
D30: Stone | J30: sf | K30: 18 | L30: =SUM(I30*K30) -> 0
D31: Brick | J31: sf | K31: 11.5 | L31: =SUM(I31*K31) -> 0
D32: Tuckpoint brick | J32: sf | K32: 3.5 | L32: =SUM(I32*K32) -> 0
D33: Power wash exterior masonry | J33: sf | K33: 0.75 | L33: =SUM(I33*K33) -> 0
A34: Painting | D34: Painting both exterior & interior (whole property) | J34: psf | K34: 3 | L34: =SUM(I34*K34) -> 0
D35: Painting exterior only | J35: psf | K35: 2 | L35: =SUM(I35*K35) -> 0
D36: Paint trim only | J36: lf | K36: 1.65 | L36: =SUM(I36*K36) -> 0
D37: Sand & refinish deck or paint deck | J37: sf | K37: 1.75 | L37: =SUM(I37*K37) -> 0
D38: Paint fence | J38: sf | K38: 1 | L38: =SUM(I38*K38) -> 0
D39: Paint detached garage | J39: sf | K39: 1 | L39: =SUM(I39*K39) -> 0
A40: Windows | D40: Windows, vinyl, average size | J40: ea | K40: 250 | L40: =SUM(I40*K40) -> 0
D41: Windows, wood, restore existing wood (historical) | J41: ea | K41: 450 | L41: =SUM(I41*K41) -> 0
D42: Window, large bay window - remove & replace | J42: ea | K42: 850 | L42: =SUM(I42*K42) -> 0
A43: ea = each | lf = linear feet | ls = lump sum | sf = square feet | psf = property sq ft | sy = square yards
A44: EXTERIOR (cont.)
A45: Category | C45: Y/N | D45: Repair Type | I45: # | J45: Unit | K45: Cost | L45: Total
A46: Garage | D46: Garage Door Only - 1 Car - 9'x7' door, manual | J46: ea | K46: 775 | L46: =SUM(I46*K46) -> 0
D47: Garage Door Only - 2 Car - 16' door, manual | J47: ea | K47: 1000 | L47: =SUM(I47*K47) -> 0
D48: Garage Door Opener Installed | J48: ea | K48: 225 | L48: =SUM(I48*K48) -> 0
D49: Reroof detached garage (rip & replace) | J49: sf | K49: 4 | L49: =SUM(I49*K49) -> 0
D50: Build new detached garage | J50: sf | K50: 30 | L50: =SUM(I50*K50) -> 0
A51: Landscaping | D51: Full landscaping makeover large lot | J51: ls | K51: 5000 | L51: =SUM(I51*K51) -> 0
D52: Full landscaping makeover medium lot | J52: ls | K52: 3500 | L52: =SUM(I52*K52) -> 0
D53: Full landscaping makeover small lot | J53: ls | K53: 2000 | L53: =SUM(I53*K53) -> 0
D54: Clean up landscaping & yard only | J54: ls | K54: 500 | L54: =SUM(I54*K54) -> 0
D55: Tree removal (per tree) | J55: ea | K55: 500 | L55: =SUM(I55*K55) -> 0
D56: Tree Planting (per tree) | J56: ea | K56: 130 | L56: =SUM(I56*K56) -> 0
A57: Concrete/Asphalt | D57: Demo existing concrete or asphalt | J57: sf | K57: 2 | L57: =SUM(I57*K57) -> 0
D58: Concrete installed for driveway/patio/sidewalk | J58: sf | K58: 7 | L58: =SUM(I58*K58) -> 0
D59: Asphalt installed in driveway | J59: sf | K59: 4 | L59: =SUM(I59*K59) -> 0
D60: Gravel installed for driveway/sidewalk | J60: sf | K60: 2 | L60: =SUM(I60*K60) -> 0
A61: Decks | D61: New deck 15'x15' (add permit if 30" off ground) | J61: ea | K61: 3000 | L61: =SUM(I61*K61) -> 0
D62: New deck 10'x10' | J62: ea | K62: 2000 | L62: =SUM(I62*K62) -> 0
D63: New deck - treated lumber | J63: sf | K63: 15 | L63: =SUM(I63*K63) -> 0
D64: New deck - cedar material | J64: sf | K64: 19 | L64: =SUM(I64*K64) -> 0
D65: Decking material replacement only | J65: sf | K65: 7 | L65: =SUM(I65*K65) -> 0
D66: Sand & refinish deck only | J66: sf | K66: 2 | L66: =SUM(I66*K66) -> 0
D67: New railings - wood | J67: lf | K67: 20 | L67: =SUM(I67*K67) -> 0
D68: New railings - metal | J68: lf | K68: 40 | L68: =SUM(I68*K68) -> 0
A69: Pergola | D69: New pergola canopy 15'x15' | J69: ea | K69: 2500 | L69: =SUM(I69*K69) -> 0
D70: New pergola canopy 10'x10' | J70: ea | K70: 2000 | L70: =SUM(I70*K70) -> 0
A71: Fence | D71: Wood fencing | J71: lf | K71: 15 | L71: =SUM(I71*K71) -> 0
D72: Wrought iron fencing | J72: lf | K72: 45 | L72: =SUM(I72*K72) -> 0
D73: Chain-link fence | J73: lf | K73: 8 | L73: =SUM(I73*K73) -> 0
A74: Pool * | D74: Pool Completely Redone ($10k to $15k) | J74: ea | K74: 10000 | L74: =SUM(I74*K74) -> 0
A75: Possible add'l Inspections needed | D75: Pool (redo plaster only) | J75: ea | K75: 4500 | L75: =SUM(I75*K75) -> 0
A76: Septic * | D76: Septic (all new system) | J76: ea | K76: 15000 | L76: =SUM(I76*K76) -> 0
A77: Possible additional Inspections, Quotes or Mediation needed | D77: Septic (new tank only) | J77: ea | K77: 5500 | L77: =SUM(I77*K77) -> 0
D78: Septic (replace leach field only) | J78: ea | K78: 3000 | L78: =SUM(I78*K78) -> 0
A80: Exterior Notes
A94: ea = each | lf = linear feet | ls = lump sum | sf = square feet | psf = property sq ft | sy = square yards
A95: INTERIOR
A96: Category | C96: Y/N | D96: Repair Type | I96: # | J96: Unit | K96: Cost | L96: Total
A97: Painting | D97: Interior painting only | J97: sf | K97: 2 | L97: =SUM(I97*K97) -> 0
D98: Add extra wall prep (damaged walls) | J98: sf | K98: 0.5 | L98: =SUM(I98*K98) -> 0
A99: Hardwood | D99: Hardwood flooring - solid wood | J99: sf | K99: 7 | L99: =SUM(I99*K99) -> 0
D100: Engineered hardwood flooring | J100: sf | K100: 6 | L100: =SUM(I100*K100) -> 0
D101: Laminate hardwood flooring | J101: sf | K101: 4 | L101: =SUM(I101*K101) -> 0
D102: Sand & refinish existing hardwood flooring | J102: sf | K102: 2 | L102: =SUM(I102*K102) -> 0
A103: Carpet / Vinyl | D103: Carpet | J103: sf | K103: 1.35 | L103: =SUM(I103*K103) -> 0
D104: Vinyl or linoleum flooring | J104: sf | K104: 2 | L104: =SUM(I104*K104) -> 0
A105: Tiling | D105: Ceramic floor tile - in kitchen | J105: sf | K105: 10 | L105: =SUM(I105*K105) -> 0
D106: Backsplash wall tile - in kitchen | J106: sf | K106: 15 | L106: =SUM(I106*K106) -> 0
D107: Ceramic floor tile - in bathrooms | J107: sf | K107: 8 | L107: =SUM(I107*K107) -> 0
D108: Shower wall tile - in bathrooms (70 sf usually) | J108: sf | K108: 9 | L108: =SUM(I108*K108) -> 0
D109: Shower accent wall tile - in bathrooms | J109: sf | K109: 16 | L109: =SUM(I109*K109) -> 0
D110: Ceramic floor tile - other areas of house | J110: sf | K110: 8 | L110: =SUM(I110*K110) -> 0
A111: Kitchen - (Grouped) | D111: High end kitchen | J111: ea | K111: 12500 | L111: =SUM(I111*K111) -> 0
A112: Includes: cabinets, counter-tops, backsplash, plumbing & electrical work & fixtures in kitchen only. Excludes: appliances, flooring, paint. | D112: Median kitchen | J112: ea | K112: 10500 | L112: =SUM(I112*K112) -> 0
D113: Low end kitchen | J113: ea | K113: 8500 | L113: =SUM(I113*K113) -> 0
D114: Low end kitchen - refinish existing cabinets | J114: ea | K114: 6500 | L114: =SUM(I114*K114) -> 0
D115: Kitchen extra custom items | J115: ea | K115: 500 | L115: =SUM(I115*K115) -> 0
A116: Appliances - (Grouped) | D116: Luxury home appliances | J116: ea | K116: 12000 | L116: =SUM(I116*K116) -> 0
...

Sheet Investment Summary
A1: Investment Summary
A2: Property Address: | C2: ='Deal Information'!$C$8 -> 123 Main Street | I2: ARV: | J2: =SUM('Deal Information'!C21) -> 200000 | M2: About the Investment Summary
A3: Beds: | B3: =SUM('Deal Information'!C9:E9) -> 3 | D3: Baths: | E3: =SUM('Deal Information'!C10:E10) -> 2 | H3: Sq Ft: | I3: =SUM('Deal Information'!C11:E11) -> 1200
A5: Executive Summary
A6: Provide a summary of the property and rehab plans here for the lender to review the lending opportunity.
B7: Closing Date: | C7: ='Deal Information'!$H$11 -> 41275
B8: Loan Amt Requested: | C8: =SUM('Deal Analyzer for Flips'!D24) -> 150000
B9: Term: | C9: =CONCATENATE(('Deal Information'!C24)," months") -> 4 months
B10: Exit Strategy: | C10: ='Deal Information'!$H$12 -> Sell to my Friend
A12: Sources & Uses
A14: Sources of Funds | D14: Amount | E14: % | G14: Uses of Funds | J14: Amount | K14: %
A15: 1st Lien Mortgage | D15: =SUM('Deal Analyzer for Flips'!D24) -> 150000 | E15: =SUM(D15/$D$20) -> 2.5586354 | G15: Purchase Price | J15: =SUM('Deal Analyzer for Flips'!D16) -> 50000 | K15: =SUM(J15/$J$20) -> 0.85287846
A16: 2nd Lien Mortgage (Seller/Private) | D16: =SUM('Deal Analyzer for Flips'!D29) -> 0 | E16: =SUM(D16/$D$20) -> 0 | G16: Closing Costs | J16: =SUM('Deal Analyzer for Flips'!D25,'Deal Analyzer for Flips'!F28:H29) -> 1125 | K16: =SUM(J16/$J$20) -> 0.019189765
A17: Equity (Borrower's Cash) | D17: ='Deal Analyzer for Flips'!D50+'Deal Analyzer for Flips'!D51+'Deal Analyzer for Flips'!D53+'Deal Analyzer for Flips'!D54+'Deal Analyzer for Flips'!D25+'Deal Analyzer for Flips'!D26-D15-D16 -> -91375 | E17: =SUM(D17/$D$20) -> -1.5586354 | G17: Hard Costs | J17: ='Deal Analyzer for Flips'!D15 -> 0 | K17: =SUM(J17/$J$20) -> 0
G18: Financing | J18: ='Deal Analyzer for Flips'!D26 -> 6000 | K18: =SUM(J18/$J$20) -> 0.10234542
G19: Soft Costs (Carry Costs) | J19: ='Deal Analyzer for Flips'!D53 -> 1500 | K19: =SUM(J19/$J$20) -> 0.025586354
C20: Total Sources | D20: =SUM(D15:D17) -> 58625 | E20: =SUM(E15:E17) -> 1 | I20: Total Uses | J20: =SUM(J15:J19) -> 58625 | K20: =SUM(K15:K19) -> 1
A22: Comparables
A23: Property 1 | D23: Type | E23: Bed | G23: Bath | H23: Size (SF) | I23: Land | J23: Year Built | K23: Distance
A24: ='Deal Information'!$C$39 -> 123 Main Street | D24: ='Deal Information'!$C$40 -> SFH | E24: =SUM('Deal Information'!C41) -> 3 | G24: =SUM('Deal Information'!C42) -> 2 | H24: =SUM('Deal Information'!C43) -> 1200 | I24: ='Deal Information'!C44 -> 1290 | J24: =SUM('Deal Information'!C45) -> 1982 | K24: ='Deal Information'!$C$46 -> 1
D25: Parking | E25: List Date | G25: List Price | H25: Sold Date | I25: Sold Price | J25: PSF | K25: DOM
D26: ='Deal Information'!$C$47 -> 1 Car | E26: ='Deal Information'!$C$48 -> 41305 | G26: =SUM('Deal Information'!C49) -> 135000 | H26: ='Deal Information'!$C$50 -> 41306 | I26: =SUM('Deal Information'!C51) -> 135000 | J26: =SUM('Deal Information'!C52) -> 65 | K26: =SUM('Deal Information'!C53) -> 0
A27: Property 2 | D27: Type | E27: Bed | G27: Bath | H27: Size (SF) | I27: Land | J27: Year Built | K27: Distance
A28: ='Deal Information'!$G$39 -> 0 | D28: ='Deal Information'!$G$40 -> 0 | E28: =SUM('Deal Information'!G41) -> 0 | G28: =SUM('Deal Information'!G42) -> 0 | H28: =SUM('Deal Information'!G43) -> 0 | I28: =SUM('Deal Information'!G44) -> 0 | J28: =SUM('Deal Information'!G45) -> 0 | K28: ='Deal Information'!$G$46 -> 0
D29: Parking | E29: List Date | G29: List Price | H29: Sold Date | I29: Sold Price | J29: PSF | K29: DOM
D30: ='Deal Information'!$G$47 -> 0 | E30: ='Deal Information'!$G$48 -> 0 | G30: =SUM('Deal Information'!G53) -> 0 | H30: ='Deal Information'!$G$50 -> 0 | I30: ='Deal Information'!G51 -> 0 | J30: ='Deal Information'!G52 -> 0 | K30: ='Deal Information'!G53 -> 0
A31: Property 3 | D31: Type | E31: Bed | G31: Bath | H31: Size (SF) | I31: Land | J31: Year Built | K31: Distance
A32: ='Deal Information'!$J$39 -> 0 | D32: ='Deal Information'!$J$40 -> 0 | E32: =SUM('Deal Information'!J41) -> 0 | G32: =SUM('Deal Information'!J42) -> 0 | H32: =SUM('Deal Information'!J43) -> 0 | I32: =SUM('Deal Information'!J44) -> 0 | J32: =SUM('Deal Information'!J45) -> 0 | K32: ='Deal Information'!$J$46 -> 0
D33: Parking | E33: List Date | G33: List Price | H33: Sold Date | I33: Sold Price | J33: PSF | K33: DOM
D34: ='Deal Information'!$J$40 -> 0 | E34: ='Deal Information'!$J$48 -> 0 | G34: =SUM('Deal Information'!J49) -> 0 | H34: ='Deal Information'!$J$50 -> 0 | I34: ='Deal Information'!$J$51 -> 0 | J34: ='Deal Information'!$J$52 -> 0 | K34: ='Deal Information'!$J$53 -> 0
A36: Attachments
B37: Tax Assessor Card
B38: Map with Comps
B39: Construction Budget / Property Inspection
B40: Deal Analyzer
B41: Photos - Interior/Exterior

Sheet Formula Data
A1: Data Tables for Repair Estimator Formulas
A2: This sheet contains data used in formulas throughout this document. Editing or Deleting parts of this sheet may change or break formulas on other tabs. Make changes at your own risk.
A7: Interior Framing Changes | B7: Sq Ft | C7: Cost | D7: Note
B8: 0 | C8: 3 | D8: This table is used to calculate the cost of framing changes based on the sqft entered by the user. The larger the sqft, the less per sqft it costs so this is a vlookup table used for the formula
B9: 1001 | C9: 5
B10: 2501 | C10: 7
B11: 3001 | C11: 9
