Workbook
Name _ProjectsArray: '[1]Project List'!$A$6:$J$49
Name BuiltIn_AutoFilter___1: #REF!
Name BuiltIn_AutoFilter___1: #REF!
Name BuiltIn_AutoFilter___1: #REF!
Name BuiltIn_AutoFilter___1_1: #REF!
Name BuiltIn_AutoFilter___1_1: #REF!
Name BuiltIn_AutoFilter___1_1: #REF!
Name BuiltIn_AutoFilter___1_2: #REF!
Name BuiltIn_AutoFilter___1_2: #REF!
Name BuiltIn_AutoFilter___1_2: #REF!
Name BuiltIn_AutoFilter___1_3: #REF!
Name BuiltIn_AutoFilter___1_3: #REF!
Name BuiltIn_AutoFilter___1_4: #REF!
Name BuiltIn_AutoFilter___1_4: #REF!
Name BuiltIn_AutoFilter___1_5: #REF!
Name BuiltIn_AutoFilter___1_5: #REF!
Name Category: OFFSET([2]Lookup!$C$2,0,0,MIN(COUNTA([2]Lookup!$C$2:$C$100)))
Name Design: '[1]Project List'!$F$6:$F$49
Name Development: '[1]Project List'!$H$6:$H$49
Name Editorial: '[1]Project List'!$G$6:$G$49
Name Endorsement: '[1]Project List'!$E$6:$E$49
Name holidays: OFFSET([3]Holidays!$A$10,1,0,COUNTA([3]Holidays!$A$11:$A$4996),1)
Name Launch: '[1]Project List'!$J$6:$J$49
Name LOB: OFFSET([2]Lookup!$D$2,0,0,MIN(COUNTA([2]Lookup!$D$2:$D$100)))
Name MPCalc1: [4]Internals!$D$4
Name MPCalc10: [4]Internals!$D$13
Name MPCalc11: [4]Internals!$D$14
Name MPCalc12: [4]Internals!$D$15
Name MPCalc2: [4]Internals!$D$5
Name MPCalc3: [4]Internals!$D$6
Name MPCalc4: [4]Internals!$D$7
Name MPCalc5: [4]Internals!$D$8
Name MPCalc6: [4]Internals!$D$9
Name MPCalc7: [4]Internals!$D$10
Name MPCalc8: [4]Internals!$D$11
Name MPCalc9: [4]Internals!$D$12
Name Ok: #REF!
Name Ok: #REF!
Name Priority: OFFSET([2]Lookup!$B$2,0,0,MIN(COUNTA([2]Lookup!$B$2:$B$100)))
Name ProcApp: #REF!
Name ProcApp: #REF!
Name ProcApp: #REF!
Name RowOffset: '[1]Project List'!$I$1
Name sort_range: '[5]Open Issues'!$3:$681
Name sort_range: '[6]Open Issues'!$3:$681
Name Spec: '[1]Project List'!$D$6:$D$49
Name Stat: '[7]Site Release Action Items List'!$E:$E
Name Status: OFFSET([2]Lookup!$A$2,0,0,MIN(COUNTA([2]Lookup!$A$2:$A$100)))
Name statuslist: #REF!
Name statuslist: #REF!
Name statuslist: #REF!
Name Testing: '[1]Project List'!$I$6:$I$49
Name valuevx: 42.314159
Name Years: OFFSET([2]Lookup!$L$2,0,0,MIN(COUNTA([2]Lookup!$L$2:$L$20)))

Sheet Deal Inputs
B1: Deal Inputs
AG2: Y | AH2: ARV
AG3: N | AH3: Purchase+Rehab
AH4: Purchase Price
B7: PROPERTY DETAILS | G7: PROJECT DETAILS
B8: Property Address: | C8: 1361 Barclay St | G8: Date: | H8: =TODAY() -> 42943
B9: Bed: | C9: 3 | G9: Occupied: | H9: Y
B10: Bath: | C10: 1 | G10: Evaluator: | H10: Shawn Tiberio
B11: Total Sqft: | C11: 1200 | G11: Closing Date: | H11: 42747
B12: Year Built: | C12: 1962 | G12: Property Type: | H12: Single-Family
B13: # of Units: | C13: 2 | G13: Parking: | H13: 2 Car Garage
B15: PROPERTY DESCRIPTION
B16: This is a 3 bed house located in a great area of the Youngstown market. Perfect for the first time home buyer. Needs some renovations.
B21: INCOME | E21: DEAL FACTORS | I21: PURCHASING THE PROPERTY
B22: Rental Income (monthly): | C22: 1250 | E22: After Repair Value: | F22: 180000 | I22: Closing Costs: | J22: 4000
E23: Purchase Price: | F23: 120000 | I23: Loan to Value %: | J23: 0.7
B24: DEAL FACTORS | E24: Property Taxes (annually): | F24: 2500 | I24: Loan Term in Months: | J24: 360
B25: Estimated Vacancy Rate: | C25: 0.05 | E25: Insurance (annually): | F25: 860 | I25: Mortgage Interest: | J25: 0.055
B26: Estimated Maintenance Costs: | C26: 0.05 | E26: HOA & Condo Fees (monthly): | F26: 50
B27: Management Fee (% of Rent): | C27: 0.08
B32: How to Use the Rental Analyzer
B33: To use the Rental Analyzer, enter all your numbers into this "Deal Input" tab. Formulas will autopopluate and automatically calculate your results on the "Deal Analyzer for Rentals" tab. White cells are editable cells.

Sheet Deal Analyzer for Rentals
B1: Deal Analyzer for Rentals
B3: INVESTMENT PROPERTY ANALYSIS
B4: Gross Rents | D4: =SUM('Deal Inputs'!C22*12) -> 15000 | F4: Annual Property Taxes | H4: =SUM('Deal Inputs'!F24:G24) -> 2500
B5: Purchase Price | D5: ='Deal Inputs'!F23 -> 120000 | F5: Annual Property Insurance | H5: =SUM('Deal Inputs'!F25) -> 860
B6: Annual Vacancy Expense | D6: =SUM(D4*'Deal Inputs'!C25) -> 750 | F6: Annual HOA Dues | H6: =SUM('Deal Inputs'!F26*12) -> 600
B7: Annual Maintenance Expense | D7: =SUM(D4*'Deal Inputs'!C26) -> 750 | F7: Annual Management Fee | H7: =SUM('Deal Inputs'!C27*D4) -> 1200
B10: CASH PURCHASE | F10: FINANCED PURCHASE
B11: Cap Rate (ROI) | F11: Return on Investment (ROI)
B12: =SUM(B14/D5) -> 0.082 | F12: =SUM(H17/H31) -> 0.11435241
B13: Annual Gross Income | C13: Monthly Gross Income | F13: Annual Gross Income | G13: Monthly Gross Income
B14: =SUM(D4-(H4+H5+H6+H7)) -> 9840 | C14: =SUM(B14/12) -> 820 | F14: =SUM(D4-(H4+H5+H6+H7+H32)) -> 4116.6869 | G14: =SUM(H17/12) -> 343.05724
B16: SUMMARY OF RETURNS after Fixed Costs | F16: SUMMARY OF RETURNS after Fixed Costs
B17: Annual Gross Income | D17: =SUM(D4-(H4+H5+H6+H7)) -> 9840 | F17: Annual Gross Income | H17: =SUM(D4-(H4+H5+H6+H7+H32)) -> 4116.6869
B18: Monthly Gross Income | D18: =SUM(B14/12) -> 820 | F18: Monthly Gross Income | H18: =SUM(H17/12) -> 343.05724
B19: Annual Gross Return on Investment (ROI) | D19: =SUM(B14/D5) -> 0.082 | F19: Annual Gross Return on Investment (ROI) | H19: =SUM(H17/H31) -> 0.11435241
B21: SUMMARY OF RETURNS with Maintenance & Vacancy | F21: SUMMARY OF RETURNS with Maintenance & Vacancy
B22: Annual Net Income | D22: =SUM(D4-D29-D6-D7) -> 8340 | F22: Annual Net Income (NOI) | H22: =SUM(D4-H32-H33-D6-D7) -> 2616.6869
B23: Monthly Net Income | D23: =SUM(D22/12) -> 695 | F23: Monthly Net Income | H23: =SUM(H22/12) -> 218.05724
B24: Annual Cash on Cash Return | D24: =SUM(D22/D28) -> 0.067258065 | F24: Annual Cash on Cash Return | H24: =SUM(H22/H31) -> 0.072685746
B26: SUMMARY OF DEAL | F26: SUMMARY OF DEAL
B27: Estimated Closing Costs | D27: =SUM('Deal Inputs'!J22) -> 4000 | F27: Loan Amount | H27: =SUM(D5*'Deal Inputs'!J23) -> 84000
B28: Total Cash Outlay at Closing | D28: =SUM(D5+D27) -> 124000 | F28: Interest Rate | H28: =SUM('Deal Inputs'!J25) -> 0.055
B29: Estimated Annual Net Expenses | D29: =SUM(H4:H7) -> 5160 | F29: Loan Terms in Months | H29: =SUM('Deal Inputs'!J24) -> 360
F30: Estimated Principal & Interest | H30: =-PMT(H28/12,H29,H27) -> 476.94276
F31: Down Payment | H31: =SUM(D5-H27) -> 36000
F32: Estimated Annual Principal & Interest | H32: =SUM(H30*12) -> 5723.3131
F33: Estimated Annual Net Expenses | H33: =SUM(H4:H7) -> 5160
B37: How to Use the Rental Analyzer
B38: To adjust numbers, make the changes on the "Deal Inputs" tab. All data on this tab "Deal Analyzer for Rentals" will automatically adjust based on the numbers entered in the "Deal Inputs" tab. Only White cells are editable.
